ethack/__init__.py
ethack/__main__.py
ethack/accountattack.py
ethack/config.toml
ethack/webattack.py
Ethack-1.0.0.dist-info/LICENSE
Ethack-1.0.0.dist-info/METADATA
Ethack-1.0.0.dist-info/WHEEL
Ethack-1.0.0.dist-info/entry_points.txt
Ethack-1.0.0.dist-info/top_level.txt
Ethack-1.0.0.dist-info/RECORD
