Metadata-Version: 2.1
Name: Ethack
Version: 1.0.0
Summary: Make cybersecurity breaches easily
Author-email: Hellom38 <dev.hellom38.hireable@gmail.com>
License: MIT License
Project-URL: repository, https://github.com/DevHellom38/Ethack
Project-URL: documentation, https://realpython.com/pypi-publish-python-package/
Keywords: hack,ethack,Hacking
Classifier: License :: OSI Approved :: MIT License
Classifier: Programming Language :: Python
Classifier: Programming Language :: Python :: 3
Requires-Python: >=3.7
License-File: LICENSE
Requires-Dist: webbot
Requires-Dist: scapy.all
Requires-Dist: email.message
Requires-Dist: datetime
Requires-Dist: twilio.rest
Requires-Dist: socket
Requires-Dist: time
Requires-Dist: smtplib
Requires-Dist: ssl
Requires-Dist: random
Requires-Dist: poplib
Requires-Dist: os
Requires-Dist: hashlib
Requires-Dist: string
Requires-Dist: tomli ; python_version < "3.11"
Provides-Extra: build
Requires-Dist: build ; extra == 'build'
Requires-Dist: twine ; extra == 'build'
Provides-Extra: dev
Requires-Dist: black ; extra == 'dev'
Requires-Dist: bumpver ; extra == 'dev'
Requires-Dist: isort ; extra == 'dev'
Requires-Dist: mypy ; extra == 'dev'
Requires-Dist: pytest ; extra == 'dev'
